{"label": "04b_L64", "model": "models/converted/rwkv7-g1d-0.4b", "data_kind": "fixed", "target_len": 64, "cache_limit_gb": null, "data_stats": {"n": 200, "min": 50, "p50": 69, "p95": 69, "max": 69, "mean": 67.6}, "stable": true, "stable_cache_gb": 1.04, "stable_peak_gb": 1.56, "stable_compress_gb": 0.43, "ms_per_step_last10": 298.4, "ms_per_step_mean": 306.7, "trace": [{"step": 0, "token_len": 69, "cache_gb": 0.65106971, "peak_gb": 1.543788876, "compress_gb": 0.4329071044921875, "ms": 351.6}, {"step": 1, "token_len": 69, "cache_gb": 0.663743446, "peak_gb": 1.555700084, "compress_gb": 0.4328765869140625, "ms": 292.4}, {"step": 2, "token_len": 50, "cache_gb": 0.77525887, "peak_gb": 1.555700084, "compress_gb": 0.432861328125, "ms": 221.3}, {"step": 3, "token_len": 67, "cache_gb": 0.816988918, "peak_gb": 1.555700084, "compress_gb": 0.432861328125, "ms": 287.2}, {"step": 4, "token_len": 65, "cache_gb": 0.88290175, "peak_gb": 1.555700084, "compress_gb": 0.432830810546875, "ms": 283.2}, {"step": 5, "token_len": 67, "cache_gb": 0.887882486, "peak_gb": 1.555700084, "compress_gb": 0.432830810546875, "ms": 288.8}, {"step": 6, "token_len": 67, "cache_gb": 0.887882486, "peak_gb": 1.555700084, "compress_gb": 0.432830810546875, "ms": 309.1}, {"step": 7, "token_len": 69, "cache_gb": 0.88789887, "peak_gb": 1.555706212, "compress_gb": 0.432830810546875, "ms": 294.8}, {"step": 8, "token_len": 69, "cache_gb": 0.88503167, "peak_gb": 1.55570622, "compress_gb": 0.432830810546875, "ms": 295.1}, {"step": 9, "token_len": 69, "cache_gb": 0.887921398, "peak_gb": 1.555706228, "compress_gb": 0.432830810546875, "ms": 295.3}, {"step": 10, "token_len": 69, "cache_gb": 0.887921398, "peak_gb": 1.555706236, "compress_gb": 0.4328155517578125, "ms": 291.0}, {"step": 11, "token_len": 69, "cache_gb": 0.887925494, "peak_gb": 1.555706244, "compress_gb": 0.4328765869140625, "ms": 292.9}, {"step": 12, "token_len": 69, "cache_gb": 0.887925494, "peak_gb": 1.555706244, "compress_gb": 0.432861328125, "ms": 293.5}, {"step": 13, "token_len": 69, "cache_gb": 0.887677686, "peak_gb": 1.55570626, "compress_gb": 0.432861328125, "ms": 306.9}, {"step": 14, "token_len": 69, "cache_gb": 0.88793983, "peak_gb": 1.55570626, "compress_gb": 0.432861328125, "ms": 301.7}, {"step": 15, "token_len": 66, "cache_gb": 0.926868214, "peak_gb": 1.55570626, "compress_gb": 0.4328460693359375, "ms": 286.3}, {"step": 16, "token_len": 69, "cache_gb": 0.926868214, "peak_gb": 1.55570626, "compress_gb": 0.4328460693359375, "ms": 298.7}, {"step": 17, "token_len": 62, "cache_gb": 0.991032022, "peak_gb": 1.55570626, "compress_gb": 0.4328460693359375, "ms": 293.9}, {"step": 18, "token_len": 69, "cache_gb": 0.991032022, "peak_gb": 1.55570626, "compress_gb": 0.4328460693359375, "ms": 296.1}, {"step": 19, "token_len": 65, "cache_gb": 0.988148438, "peak_gb": 1.55570626, "compress_gb": 0.4328765869140625, "ms": 282.9}, {"step": 20, "token_len": 69, "cache_gb": 0.986837718, "peak_gb": 1.55570626, "compress_gb": 0.43310546875, "ms": 331.3}, {"step": 21, "token_len": 69, "cache_gb": 0.989459158, "peak_gb": 1.55570626, "compress_gb": 0.43310546875, "ms": 305.7}, {"step": 22, "token_len": 69, "cache_gb": 0.991032022, "peak_gb": 1.55570626, "compress_gb": 0.43310546875, "ms": 302.5}, {"step": 23, "token_len": 69, "cache_gb": 0.991032022, "peak_gb": 1.55570626, "compress_gb": 0.43310546875, "ms": 327.2}, {"step": 24, "token_len": 69, "cache_gb": 0.991032022, "peak_gb": 1.55570626, "compress_gb": 0.4330902099609375, "ms": 304.2}, {"step": 25, "token_len": 69, "cache_gb": 0.989997782, "peak_gb": 1.55570626, "compress_gb": 0.4330902099609375, "ms": 308.3}, {"step": 26, "token_len": 69, "cache_gb": 0.991046358, "peak_gb": 1.55570626, "compress_gb": 0.4323577880859375, "ms": 326.6}, {"step": 27, "token_len": 69, "cache_gb": 0.990259926, "peak_gb": 1.55570626, "compress_gb": 0.4323577880859375, "ms": 293.1}, {"step": 28, "token_len": 69, "cache_gb": 0.986852054, "peak_gb": 1.55570626, "compress_gb": 0.4323577880859375, "ms": 294.7}, {"step": 29, "token_len": 69, "cache_gb": 0.991202006, "peak_gb": 1.555706388, "compress_gb": 0.4323577880859375, "ms": 343.1}, {"step": 30, "token_len": 65, "cache_gb": 0.989629142, "peak_gb": 1.555706388, "compress_gb": 0.4323577880859375, "ms": 320.0}, {"step": 31, "token_len": 69, "cache_gb": 0.991202006, "peak_gb": 1.555706388, "compress_gb": 0.432464599609375, "ms": 296.7}, {"step": 32, "token_len": 62, "cache_gb": 0.991202006, "peak_gb": 1.555706388, "compress_gb": 0.432464599609375, "ms": 290.3}, {"step": 33, "token_len": 69, "cache_gb": 0.989629142, "peak_gb": 1.555706388, "compress_gb": 0.432464599609375, "ms": 296.0}, {"step": 34, "token_len": 69, "cache_gb": 0.995363542, "peak_gb": 1.555706388, "compress_gb": 0.432464599609375, "ms": 297.5}, {"step": 35, "token_len": 69, "cache_gb": 0.991693526, "peak_gb": 1.555706388, "compress_gb": 0.432464599609375, "ms": 296.3}, {"step": 36, "token_len": 63, "cache_gb": 1.029797062, "peak_gb": 1.555706388, "compress_gb": 0.432464599609375, "ms": 292.6}, {"step": 37, "token_len": 69, "cache_gb": 1.034781894, "peak_gb": 1.555706452, "compress_gb": 0.432464599609375, "ms": 339.4}, {"step": 38, "token_len": 69, "cache_gb": 1.03478599, "peak_gb": 1.55570646, "compress_gb": 0.432464599609375, "ms": 337.4}, {"step": 39, "token_len": 69, "cache_gb": 1.035080902, "peak_gb": 1.55570646, "compress_gb": 0.432464599609375, "ms": 339.0}, {"step": 40, "token_len": 69, "cache_gb": 1.035084998, "peak_gb": 1.555706476, "compress_gb": 0.432464599609375, "ms": 340.7}, {"step": 41, "token_len": 69, "cache_gb": 1.035084998, "peak_gb": 1.555706476, "compress_gb": 0.432464599609375, "ms": 341.0}, {"step": 42, "token_len": 69, "cache_gb": 1.035084998, "peak_gb": 1.555706476, "compress_gb": 0.432464599609375, "ms": 336.3}, {"step": 43, "token_len": 69, "cache_gb": 1.035084998, "peak_gb": 1.555706476, "compress_gb": 0.432464599609375, "ms": 337.9}, {"step": 44, "token_len": 69, "cache_gb": 1.033774278, "peak_gb": 1.555706476, "compress_gb": 0.432464599609375, "ms": 295.4}, {"step": 45, "token_len": 69, "cache_gb": 1.035084998, "peak_gb": 1.555706476, "compress_gb": 0.432464599609375, "ms": 338.8}, {"step": 46, "token_len": 69, "cache_gb": 1.035388102, "peak_gb": 1.555706476, "compress_gb": 0.432464599609375, "ms": 342.7}, {"step": 47, "token_len": 69, "cache_gb": 1.03329095, "peak_gb": 1.555706476, "compress_gb": 0.432464599609375, "ms": 296.4}, {"step": 48, "token_len": 65, "cache_gb": 1.029620934, "peak_gb": 1.555706476, "compress_gb": 0.432464599609375, "ms": 280.1}, {"step": 49, "token_len": 69, "cache_gb": 1.035388102, "peak_gb": 1.555706476, "compress_gb": 0.432464599609375, "ms": 338.0}, {"step": 50, "token_len": 69, "cache_gb": 1.032504518, "peak_gb": 1.555706476, "compress_gb": 0.432464599609375, "ms": 296.1}, {"step": 51, "token_len": 66, "cache_gb": 1.032242374, "peak_gb": 1.555706476, "compress_gb": 0.432464599609375, "ms": 282.2}, {"step": 52, "token_len": 69, "cache_gb": 1.035388102, "peak_gb": 1.555706476, "compress_gb": 0.432464599609375, "ms": 336.3}, {"step": 53, "token_len": 65, "cache_gb": 1.024902342, "peak_gb": 1.555706476, "compress_gb": 0.432464599609375, "ms": 280.3}, {"step": 54, "token_len": 69, "cache_gb": 1.035388102, "peak_gb": 1.555706476, "compress_gb": 0.432525634765625, "ms": 334.6}, {"step": 55, "token_len": 69, "cache_gb": 1.035388102, "peak_gb": 1.555706476, "compress_gb": 0.432525634765625, "ms": 340.0}, {"step": 56, "token_len": 69, "cache_gb": 1.035388102, "peak_gb": 1.555706476, "compress_gb": 0.4325714111328125, "ms": 336.3}, {"step": 57, "token_len": 62, "cache_gb": 1.035388102, "peak_gb": 1.555706476, "compress_gb": 0.4325714111328125, "ms": 287.5}, {"step": 58, "token_len": 69, "cache_gb": 1.035394246, "peak_gb": 1.55570662, "compress_gb": 0.4325714111328125, "ms": 340.8}, {"step": 59, "token_len": 69, "cache_gb": 1.035394246, "peak_gb": 1.55570662, "compress_gb": 0.43255615234375, "ms": 340.3}, {"step": 60, "token_len": 69, "cache_gb": 1.031199942, "peak_gb": 1.55570662, "compress_gb": 0.43255615234375, "ms": 299.0}, {"step": 61, "token_len": 69, "cache_gb": 1.031986374, "peak_gb": 1.55570662, "compress_gb": 0.43255615234375, "ms": 293.8}, {"step": 62, "token_len": 62, "cache_gb": 1.034869958, "peak_gb": 1.55570662, "compress_gb": 0.43255615234375, "ms": 286.0}, {"step": 63, "token_len": 69, "cache_gb": 1.03434567, "peak_gb": 1.55570662, "compress_gb": 0.43255615234375, "ms": 295.4}, {"step": 64, "token_len": 69, "cache_gb": 1.034869958, "peak_gb": 1.55570662, "compress_gb": 0.43255615234375, "ms": 294.8}, {"step": 65, "token_len": 69, "cache_gb": 1.03565639, "peak_gb": 1.55570662, "compress_gb": 0.43255615234375, "ms": 295.6}, {"step": 66, "token_len": 69, "cache_gb": 1.03434567, "peak_gb": 1.55570662, "compress_gb": 0.43255615234375, "ms": 295.3}, {"step": 67, "token_len": 69, "cache_gb": 1.03434567, "peak_gb": 1.55570662, "compress_gb": 0.43255615234375, "ms": 295.6}, {"step": 68, "token_len": 69, "cache_gb": 1.038539974, "peak_gb": 1.55570662, "compress_gb": 0.43255615234375, "ms": 334.3}, {"step": 69, "token_len": 69, "cache_gb": 1.03434567, "peak_gb": 1.55570662, "compress_gb": 0.43255615234375, "ms": 296.2}, {"step": 70, "token_len": 69, "cache_gb": 1.038542022, "peak_gb": 1.55570662, "compress_gb": 0.43255615234375, "ms": 336.0}, {"step": 71, "token_len": 69, "cache_gb": 1.038546118, "peak_gb": 1.555706724, "compress_gb": 0.4325103759765625, "ms": 337.1}, {"step": 72, "token_len": 50, "cache_gb": 1.03146823, "peak_gb": 1.555706724, "compress_gb": 0.4325103759765625, "ms": 220.8}, {"step": 73, "token_len": 62, "cache_gb": 1.039594694, "peak_gb": 1.555706724, "compress_gb": 0.432525634765625, "ms": 287.8}, {"step": 74, "token_len": 69, "cache_gb": 1.038808262, "peak_gb": 1.555706724, "compress_gb": 0.432525634765625, "ms": 297.0}, {"step": 75, "token_len": 69, "cache_gb": 1.03959879, "peak_gb": 1.555706724, "compress_gb": 0.432525634765625, "ms": 339.4}, {"step": 76, "token_len": 69, "cache_gb": 1.03959879, "peak_gb": 1.555706724, "compress_gb": 0.432525634765625, "ms": 341.9}, {"step": 77, "token_len": 69, "cache_gb": 1.03959879, "peak_gb": 1.555706724, "compress_gb": 0.432525634765625, "ms": 297.3}, {"step": 78, "token_len": 69, "cache_gb": 1.03959879, "peak_gb": 1.555706724, "compress_gb": 0.432525634765625, "ms": 348.2}, {"step": 79, "token_len": 69, "cache_gb": 1.039074502, "peak_gb": 1.555706724, "compress_gb": 0.432525634765625, "ms": 299.2}, {"step": 80, "token_len": 67, "cache_gb": 1.03435591, "peak_gb": 1.555706724, "compress_gb": 0.432525634765625, "ms": 288.9}, {"step": 81, "token_len": 69, "cache_gb": 1.03959879, "peak_gb": 1.555706724, "compress_gb": 0.43255615234375, "ms": 342.3}, {"step": 82, "token_len": 65, "cache_gb": 1.034880198, "peak_gb": 1.555706724, "compress_gb": 0.43255615234375, "ms": 281.3}, {"step": 83, "token_len": 63, "cache_gb": 1.042744518, "peak_gb": 1.555706724, "compress_gb": 0.43255615234375, "ms": 289.0}, {"step": 84, "token_len": 69, "cache_gb": 1.043006662, "peak_gb": 1.555706724, "compress_gb": 0.43255615234375, "ms": 296.9}, {"step": 85, "token_len": 69, "cache_gb": 1.044055238, "peak_gb": 1.555706724, "compress_gb": 0.43255615234375, "ms": 339.9}, {"step": 86, "token_len": 69, "cache_gb": 1.044055238, "peak_gb": 1.555706724, "compress_gb": 0.43255615234375, "ms": 338.5}, {"step": 87, "token_len": 69, "cache_gb": 1.039860934, "peak_gb": 1.555706724, "compress_gb": 0.43255615234375, "ms": 297.3}, {"step": 88, "token_len": 69, "cache_gb": 1.039860934, "peak_gb": 1.555706724, "compress_gb": 0.43255615234375, "ms": 295.5}, {"step": 89, "token_len": 69, "cache_gb": 1.044055238, "peak_gb": 1.555706724, "compress_gb": 0.43255615234375, "ms": 296.0}, {"step": 90, "token_len": 69, "cache_gb": 1.043268806, "peak_gb": 1.555706724, "compress_gb": 0.432525634765625, "ms": 303.2}, {"step": 91, "token_len": 69, "cache_gb": 1.042482374, "peak_gb": 1.555706724, "compress_gb": 0.432525634765625, "ms": 294.2}, {"step": 92, "token_len": 69, "cache_gb": 1.039860934, "peak_gb": 1.555706724, "compress_gb": 0.432647705078125, "ms": 295.5}, {"step": 93, "token_len": 69, "cache_gb": 1.040385222, "peak_gb": 1.555706724, "compress_gb": 0.432647705078125, "ms": 297.3}, {"step": 94, "token_len": 69, "cache_gb": 1.044055238, "peak_gb": 1.555706724, "compress_gb": 0.432647705078125, "ms": 300.8}, {"step": 95, "token_len": 69, "cache_gb": 1.040385222, "peak_gb": 1.555706724, "compress_gb": 0.432647705078125, "ms": 296.7}, {"step": 96, "token_len": 69, "cache_gb": 1.043793094, "peak_gb": 1.555706724, "compress_gb": 0.432647705078125, "ms": 297.3}, {"step": 97, "token_len": 69, "cache_gb": 1.040123078, "peak_gb": 1.555706724, "compress_gb": 0.432647705078125, "ms": 301.4}, {"step": 98, "token_len": 69, "cache_gb": 1.041695942, "peak_gb": 1.555706724, "compress_gb": 0.432647705078125, "ms": 299.0}, {"step": 99, "token_len": 69, "cache_gb": 1.041171654, "peak_gb": 1.555706724, "compress_gb": 0.432647705078125, "ms": 298.8}]}
